aet/__init__.py
aet/__main__.py
aet/client.py
aet/commands.py
aet/config.py
aet/loggers.py
aet-0.1.4.dist-info/LICENSE
aet-0.1.4.dist-info/METADATA
aet-0.1.4.dist-info/WHEEL
aet-0.1.4.dist-info/entry_points.txt
aet-0.1.4.dist-info/top_level.txt
aet-0.1.4.dist-info/RECORD
