Metadata-Version: 2.1
Name: aet
Version: 0.1.4
Summary: Command line interface for working with aet services.
Home-page: https://github.com/aet-repos/cli
Author: Tom Waterman
Author-email: tjwaterman99@gmail.com
License: UNKNOWN
Platform: UNKNOWN
License-File: LICENSE
Requires-Dist: requests (<2.24.0)
Requires-Dist: click (==8.0.1)
Requires-Dist: PyYAML (==5.4.1)
